{
  "brand": {
    "name": "FOP",
    "fullName": "Fuzion Operating Platform",
    "missionControl": "Mission Control",
    "tagline": "The Operating Platform for Building Protection",
    "lifecycle": "BUILD • ADVISE • PROTECT",
    "promise": "Buildings Under Protection™",
    "architecture": "F Mark, FOP Wordmark, Living F"
  },
  "color": {
    "background": {
      "white": {
        "value": "#FFFFFF",
        "usage": "Primary application surface"
      },
      "appBackground": {
        "value": "#F8FAFC",
        "usage": "Light architectural workspace"
      }
    },
    "text": {
      "primaryNavy": {
        "value": "#071223",
        "usage": "Primary typography and default F Mark colour"
      },
      "secondarySlate": {
        "value": "#334155",
        "usage": "Secondary typography"
      }
    },
    "lifecycle": {
      "build": {
        "value": "#126BFF",
        "name": "Electric Royal Blue",
        "usage": "BUILD lifecycle signal and Living F middle arm"
      },
      "advise": {
        "value": "#BFC5CE",
        "name": "Platinum Silver",
        "usage": "ADVISE lifecycle signal and Living F top arm"
      },
      "protect": {
        "value": "#86EE62",
        "name": "Pastel Highlighter Green",
        "usage": "PROTECT lifecycle signal and Living F vertical stem"
      }
    },
    "halo": {
      "value": "#FF7A66",
      "name": "Coral Halo",
      "usage": "Living F certification halo only after backend Protected-State approval"
    },
    "border": {
      "value": "#E2E8F0",
      "usage": "Subtle cool grey borders"
    }
  },
  "assets": {
    "fMark": {
      "purpose": "Primary application icon",
      "rules": "Flat, one-colour, no glow, no halo, no text, no embedded lifecycle labels"
    },
    "fopWordmark": {
      "purpose": "Corporate identity",
      "structure": "F Mark plus FUZION, OPERATING PLATFORM™, BUILD • ADVISE • PROTECT, Buildings Under Protection™"
    },
    "livingF": {
      "purpose": "Lifecycle and certification mark",
      "rules": "Never use as the permanent application logo. Coral halo appears only after backend Protected-State approval."
    }
  },
  "cssVariables": {
    "background": "--background",
    "appBackground": "--app-background",
    "build": "--fop-build",
    "advise": "--fop-advise",
    "protect": "--fop-protect",
    "halo": "--fop-halo",
    "textPrimary": "--text-primary"
  }
}
